tun/__init__.py
tun/data_types.py
tun/errors.py
tun/pint_tools.py
tun/pint_units.txt
tun/py.typed
tun/quantity_types.py
tun/unit_collections.py
tun/unit_types.py
tun-0.3.0.dist-info/LICENSE
tun-0.3.0.dist-info/METADATA
tun-0.3.0.dist-info/WHEEL
tun-0.3.0.dist-info/RECORD
