Metadata-Version: 2.1
Name: tun
Version: 0.3.0
Summary: A Python library for object-oriented parameters, physical quantities and units with a strong support for typing.
Home-page: https://gitlab.com/c4dht/tun
License: GNU AGPLv3
Author: Paul Kernstock
Author-email: paul.kernstock@posteo.de
Maintainer: Paul Kernstock
Maintainer-email: paul.kernstock@posteo.de
Requires-Python: >=3.9,<3.13
Classifier: License :: Other/Proprietary License
Classifier: Programming Language :: Python :: 3
Classifier: Programming Language :: Python :: 3.9
Classifier: Programming Language :: Python :: 3.10
Classifier: Programming Language :: Python :: 3.11
Classifier: Programming Language :: Python :: 3.12
Requires-Dist: numpy (>=1,<2)
Requires-Dist: pandas (>=2,<3)
Requires-Dist: pandas-stubs (>=2,<3)
Requires-Dist: pint[pandas] (>=0.22,<0.23)
Requires-Dist: scipy (>=1,<2)
Project-URL: Repository, https://gitlab.com/c4dht/tun
